manageprojects/__init__.py
manageprojects/__main__.py
manageprojects/constants.py
manageprojects/cookiecutter_api.py
manageprojects/cookiecutter_generator.py
manageprojects/cookiecutter_templates.py
manageprojects/data_classes.py
manageprojects/exceptions.py
manageprojects/format_file.py
manageprojects/git.py
manageprojects/install_python.py
manageprojects/install_python_example.sh
manageprojects/overwrite.py
manageprojects/patching.py
manageprojects/setup_python.py
manageprojects/setup_python_example.sh
manageprojects/cli_app/__init__.py
manageprojects/cli_app/manage.py
manageprojects/cli_app/shell_completion.py
manageprojects/cli_dev/__init__.py
manageprojects/cli_dev/__main__.py
manageprojects/cli_dev/code_style.py
manageprojects/cli_dev/git_hooks.py
manageprojects/cli_dev/packaging.py
manageprojects/cli_dev/shell_completion.py
manageprojects/cli_dev/testing.py
manageprojects/cli_dev/update_readme_history.py
manageprojects/test_utils/__init__.py
manageprojects/test_utils/click_cli_utils.py
manageprojects/test_utils/git_utils.py
manageprojects/test_utils/logs.py
manageprojects/test_utils/project_setup.py
manageprojects/test_utils/subprocess.py
manageprojects/test_utils/temp_utils.py
manageprojects/tests/__init__.py
manageprojects/tests/base.py
manageprojects/tests/docwrite_macros_install_python.py
manageprojects/tests/docwrite_macros_setup_python.py
manageprojects/tests/test_cli.py
manageprojects/tests/test_cookiecutter_api.py
manageprojects/tests/test_cookiecutter_generator.py
manageprojects/tests/test_cookiecutter_templates.py
manageprojects/tests/test_doc_write.py
manageprojects/tests/test_doctests.py
manageprojects/tests/test_format_file.py
manageprojects/tests/test_install_python.py
manageprojects/tests/test_overwrite.py
manageprojects/tests/test_patching.py
manageprojects/tests/test_patching_make_git_diff_1.snapshot.patch
manageprojects/tests/test_project_setup.py
manageprojects/tests/test_readme.py
manageprojects/tests/test_readme_history.py
manageprojects-0.27.2.dist-info/METADATA
manageprojects-0.27.2.dist-info/WHEEL
manageprojects-0.27.2.dist-info/entry_points.txt
manageprojects-0.27.2.dist-info/licenses/LICENSE
manageprojects-0.27.2.dist-info/RECORD
