Metadata-Version: 2.4
Name: manageprojects
Version: 0.27.2
Summary: Manage Python / Django projects
Project-URL: Documentation, https://github.com/jedie/manageprojects
Project-URL: Source, https://github.com/jedie/manageprojects
Author-email: Jens Diemer <mamageprojects@jensdiemer.de>
License: GPL-3.0-or-later
License-File: LICENSE
Requires-Python: >=3.12
Requires-Dist: cli-base-utilities>=0.27.1
Requires-Dist: codespell
Requires-Dist: cookiecutter>=2.4.0
Requires-Dist: editorconfig
Requires-Dist: rich
Requires-Dist: ruff
Requires-Dist: tomlkit
Requires-Dist: ty
Requires-Dist: tyro
